Workbook

Sheet Start Here
A1: Renovation Allowance & Change-Order Control
A4: This workbook answers one question your budget spreadsheet cannot: what will this project actually cost me, given what I have already signed and what I still owe back?
A6: How to use it
A7: 1. Setup - project name, contingency reserve, currency. Ten minutes.
A8: 2. Cost Control - one row per budget line. Type the original budget and what you have signed. The rest is calculated.
A9: 3. Payments - every payment, one row. 'Paid to date' on Cost Control is summed from here, never typed.
A10: 4. Change Orders - every change with its own number. Only rows marked Approved count, and they raise the revised budget automatically.
A11: 5. Allowances - items priced as a spending allowance before the actual product is chosen (tile, lighting, counters). This sheet is where silent overruns and forgotten credits show up.
A12: 6. Contingency - the reserve and what has been drawn from it. It is not a slush fund.
A13: 7. Summary - the four numbers that matter, plus checks that tell you what to fix.
A14: 8. Assumptions - write down what is excluded. An estimate is only honest with its exclusions next to it.
A16: Colour code
... A23: The yellow rows describe a $45,000 kitchen renovation that ends up projected $6,500 over its revised budget. The guide walks through exactly those numbers. Delete the examples once you understand them.

Sheet Setup
A1: Setting | B1: Your value | C1: Notes
A2: Project name | B2: Kitchen renovation (EXAMPLE) | C2: Anything you will recognise later
A3: Property address | C3: Optional
A4: Currency symbol | B4: $ | C4: Used in the labels only
A5: Contingency reserve (USD) | B5: 4500 | C5: EXAMPLE: 10% of a $45,000 line budget. Research puts 10-20% as a floor and 25-30% for structural work.
A6: Today's date | B6: 2026-06-20 | C6: Update when you review the sheet
A7: Who approves change orders | B7: Owner | C7: Write the name, not the role, if more than one person can approve
A8: Who approves contingency draws | B8: Owner | C8: Same: a name
A9: Review cadence | B9: Monthly, plus after every signed change order | C9: The review is what makes the numbers true

Sheet Cost Control
A1: Line | B1: Category | C1: What it covers | D1: Original budget | E1: Original committed | F1: Approved changes | G1: Revised budget | H1: Committed total | I1: Paid to date | J1: Unpaid committed | K1: Forecast to complete | L1: Projected final | M1: Variance vs revised | N1: Status
A2: K-01 | B2: Demolition | C2: Strip kitchen, remove a non-load-bearing partition | D2: 3000 | E2: 2800 | F2: =IF($A2="","",SUMIF('Change Orders'!$C$2:$C$21,$A2,'Change Orders'!$G$2:$G$21)) | G2: =IF($A2="","",N($D2)+N($F2)) | H2: =IF($A2="","",N($E2)+N($F2)) | I2: =IF($A2="","",SUMIF(Payments!$B$2:$B$31,$A2,Payments!$D$2:$D$31)) | J2: =IF($A2="","",MAX(0,N($H2)-N($I2))) | K2: 0 | L2: =IF($A2="","",N($I2)+N($J2)+N($K2)) | M2: =IF($A2="","",N($G2)-N($L2)) | N2: =IF($A2="","",IF(N($L2)>N($G2),"OVER",IF(N($L2)=N($G2),"ON PLAN","UNDER")))
A3: K-02 | B3: Millwork | C3: Cabinet package, delivered and installed | D3: 12000 | E3: 12500 | F3: =IF($A3="","",SUMIF('Change Orders'!$C$2:$C$21,$A3,'Change Orders'!$G$2:$G$21)) | G3: =IF($A3="","",N($D3)+N($F3)) | H3: =IF($A3="","",N($E3)+N($F3)) | I3: =IF($A3="","",SUMIF(Payments!$B$2:$B$31,$A3,Payments!$D$2:$D$31)) | J3: =IF($A3="","",MAX(0,N($H3)-N($I3))) | K3: 0 | L3: =IF($A3="","",N($I3)+N($J3)+N($K3)) | M3: =IF($A3="","",N($G3)-N($L3)) | N3: =IF($A3="","",IF(N($L3)>N($G3),"OVER",IF(N($L3)=N($G3),"ON PLAN","UNDER")))
A4: K-03 | B4: Surfaces | C4: Countertop allowance, made when the slab was chosen | D4: 7500 | E4: 7500 | F4: =IF($A4="","",SUMIF('Change Orders'!$C$2:$C$21,$A4,'Change Orders'!$G$2:$G$21)) | G4: =IF($A4="","",N($D4)+N($F4)) | H4: =IF($A4="","",N($E4)+N($F4)) | I4: =IF($A4="","",SUMIF(Payments!$B$2:$B$31,$A4,Payments!$D$2:$D$31)) | J4: =IF($A4="","",MAX(0,N($H4)-N($I4))) | K4: 0 | L4: =IF($A4="","",N($I4)+N($J4)+N($K4)) | M4: =IF($A4="","",N($G4)-N($L4)) | N4: =IF($A4="","",IF(N($L4)>N($G4),"OVER",IF(N($L4)=N($G4),"ON PLAN","UNDER")))
A5: K-04 | B5: Tile & flooring | C5: Floor tile plus installation labour | D5: 6000 | E5: 5900 | F5: =IF($A5="","",SUMIF('Change Orders'!$C$2:$C$21,$A5,'Change Orders'!$G$2:$G$21)) | G5: =IF($A5="","",N($D5)+N($F5)) | H5: =IF($A5="","",N($E5)+N($F5)) | I5: =IF($A5="","",SUMIF(Payments!$B$2:$B$31,$A5,Payments!$D$2:$D$31)) | J5: =IF($A5="","",MAX(0,N($H5)-N($I5))) | K5: 550 | L5: =IF($A5="","",N($I5)+N($J5)+N($K5)) | M5: =IF($A5="","",N($G5)-N($L5)) | N5: =IF($A5="","",IF(N($L5)>N($G5),"OVER",IF(N($L5)=N($G5),"ON PLAN","UNDER")))
A6: K-05 | B6: Electrical | C6: Rewire, plus one added circuit (change order) | D6: 4500 | E6: 4800 | F6: =IF($A6="","",SUMIF('Change Orders'!$C$2:$C$21,$A6,'Change Orders'!$G$2:$G$21)) | G6: =IF($A6="","",N($D6)+N($F6)) | H6: =IF($A6="","",N($E6)+N($F6)) | I6: =IF($A6="","",SUMIF(Payments!$B$2:$B$31,$A6,Payments!$D$2:$D$31)) | J6: =IF($A6="","",MAX(0,N($H6)-N($I6))) | K6: 0 | L6: =IF($A6="","",N($I6)+N($J6)+N($K6)) | M6: =IF($A6="","",N($G6)-N($L6)) | N6: =IF($A6="","",IF(N($L6)>N($G6),"OVER",IF(N($L6)=N($G6),"ON PLAN","UNDER")))
A7: K-06 | B7: Paint & finish | C7: Painting and trim, not yet contracted | D7: 3000 | E7: 0 | F7: =IF($A7="","",SUMIF('Change Orders'!$C$2:$C$21,$A7,'Change Orders'!$G$2:$G$21)) | G7: =IF($A7="","",N($D7)+N($F7)) | H7: =IF($A7="","",N($E7)+N($F7)) | I7: =IF($A7="","",SUMIF(Payments!$B$2:$B$31,$A7,Payments!$D$2:$D$31)) | J7: =IF($A7="","",MAX(0,N($H7)-N($I7))) | K7: 3750 | L7: =IF($A7="","",N($I7)+N($J7)+N($K7)) | M7: =IF($A7="","",N($G7)-N($L7)) | N7: =IF($A7="","",IF(N($L7)>N($G7),"OVER",IF(N($L7)=N($G7),"ON PLAN","UNDER")))
A8: K-07 | B8: Design & permits | C8: Design fee and building permit | D8: 1200 | E8: 1200 | F8: =IF($A8="","",SUMIF('Change Orders'!$C$2:$C$21,$A8,'Change Orders'!$G$2:$G$21)) | G8: =IF($A8="","",N($D8)+N($F8)) | H8: =IF($A8="","",N($E8)+N($F8)) | I8: =IF($A8="","",SUMIF(Payments!$B$2:$B$31,$A8,Payments!$D$2:$D$31)) | J8: =IF($A8="","",MAX(0,N($H8)-N($I8))) | K8: 0 | L8: =IF($A8="","",N($I8)+N($J8)+N($K8)) | M8: =IF($A8="","",N($G8)-N($L8)) | N8: =IF($A8="","",IF(N($L8)>N($G8),"OVER",IF(N($L8)=N($G8),"ON PLAN","UNDER")))
A9: K-08 | B9: Appliances | C9: Range, hood, dishwasher - not ordered yet | D9: 5000 | E9: 0 | F9: =IF($A9="","",SUMIF('Change Orders'!$C$2:$C$21,$A9,'Change Orders'!$G$2:$G$21)) | G9: =IF($A9="","",N($D9)+N($F9)) | H9: =IF($A9="","",N($E9)+N($F9)) | I9: =IF($A9="","",SUMIF(Payments!$B$2:$B$31,$A9,Payments!$D$2:$D$31)) | J9: =IF($A9="","",MAX(0,N($H9)-N($I9))) | K9: 5600 | L9: =IF($A9="","",N($I9)+N($J9)+N($K9)) | M9: =IF($A9="","",N($G9)-N($L9)) | N9: =IF($A9="","",IF(N($L9)>N($G9),"OVER",IF(N($L9)=N($G9),"ON PLAN","UNDER")))
A10: K-09 | B10: Other | C10: Project management fee | D10: 2800 | E10: 2800 | F10: =IF($A10="","",SUMIF('Change Orders'!$C$2:$C$21,$A10,'Change Orders'!$G$2:$G$21)) | G10: =IF($A10="","",N($D10)+N($F10)) | H10: =IF($A10="","",N($E10)+N($F10)) | I10: =IF($A10="","",SUMIF(Payments!$B$2:$B$31,$A10,Payments!$D$2:$D$31)) | J10: =IF($A10="","",MAX(0,N($H10)-N($I10))) | K10: 0 | L10: =IF($A10="","",N($I10)+N($J10)+N($K10)) | M10: =IF($A10="","",N($G10)-N($L10)) | N10: =IF($A10="","",IF(N($L10)>N($G10),"OVER",IF(N($L10)=N($G10),"ON PLAN","UNDER")))
F11: =IF($A11="","",SUMIF('Change Orders'!$C$2:$C$21,$A11,'Change Orders'!$G$2:$G$21)) | G11: =IF($A11="","",N($D11)+N($F11)) | H11: =IF($A11="","",N($E11)+N($F11)) | I11: =IF($A11="","",SUMIF(Payments!$B$2:$B$31,$A11,Payments!$D$2:$D$31)) | J11: =IF($A11="","",MAX(0,N($H11)-N($I11))) | L11: =IF($A11="","",N($I11)+N($J11)+N($K11)) | M11: =IF($A11="","",N($G11)-N($L11)) | N11: =IF($A11="","",IF(N($L11)>N($G11),"OVER",IF(N($L11)=N($G11),"ON PLAN","UNDER")))
F12: =IF($A12="","",SUMIF('Change Orders'!$C$2:$C$21,$A12,'Change Orders'!$G$2:$G$21)) | G12: =IF($A12="","",N($D12)+N($F12)) | H12: =IF($A12="","",N($E12)+N($F12)) | I12: =IF($A12="","",SUMIF(Payments!$B$2:$B$31,$A12,Payments!$D$2:$D$31)) | J12: =IF($A12="","",MAX(0,N($H12)-N($I12))) | L12: =IF($A12="","",N($I12)+N($J12)+N($K12)) | M12: =IF($A12="","",N($G12)-N($L12)) | N12: =IF($A12="","",IF(N($L12)>N($G12),"OVER",IF(N($L12)=N($G12),"ON PLAN","UNDER")))
F13: =IF($A13="","",SUMIF('Change Orders'!$C$2:$C$21,$A13,'Change Orders'!$G$2:$G$21)) | G13: =IF($A13="","",N($D13)+N($F13)) | H13: =IF($A13="","",N($E13)+N($F13)) | I13: =IF($A13="","",SUMIF(Payments!$B$2:$B$31,$A13,Payments!$D$2:$D$31)) | J13: =IF($A13="","",MAX(0,N($H13)-N($I13))) | L13: =IF($A13="","",N($I13)+N($J13)+N($K13)) | M13: =IF($A13="","",N($G13)-N($L13)) | N13: =IF($A13="","",IF(N($L13)>N($G13),"OVER",IF(N($L13)=N($G13),"ON PLAN","UNDER")))
F14: =IF($A14="","",SUMIF('Change Orders'!$C$2:$C$21,$A14,'Change Orders'!$G$2:$G$21)) | G14: =IF($A14="","",N($D14)+N($F14)) | H14: =IF($A14="","",N($E14)+N($F14)) | I14: =IF($A14="","",SUMIF(Payments!$B$2:$B$31,$A14,Payments!$D$2:$D$31)) | J14: =IF($A14="","",MAX(0,N($H14)-N($I14))) | L14: =IF($A14="","",N($I14)+N($J14)+N($K14)) | M14: =IF($A14="","",N($G14)-N($L14)) | N14: =IF($A14="","",IF(N($L14)>N($G14),"OVER",IF(N($L14)=N($G14),"ON PLAN","UNDER")))
F15: =IF($A15="","",SUMIF('Change Orders'!$C$2:$C$21,$A15,'Change Orders'!$G$2:$G$21)) | G15: =IF($A15="","",N($D15)+N($F15)) | H15: =IF($A15="","",N($E15)+N($F15)) | I15: =IF($A15="","",SUMIF(Payments!$B$2:$B$31,$A15,Payments!$D$2:$D$31)) | J15: =IF($A15="","",MAX(0,N($H15)-N($I15))) | L15: =IF($A15="","",N($I15)+N($J15)+N($K15)) | M15: =IF($A15="","",N($G15)-N($L15)) | N15: =IF($A15="","",IF(N($L15)>N($G15),"OVER",IF(N($L15)=N($G15),"ON PLAN","UNDER")))
F16: =IF($A16="","",SUMIF('Change Orders'!$C$2:$C$21,$A16,'Change Orders'!$G$2:$G$21)) | G16: =IF($A16="","",N($D16)+N($F16)) | H16: =IF($A16="","",N($E16)+N($F16)) | I16: =IF($A16="","",SUMIF(Payments!$B$2:$B$31,$A16,Payments!$D$2:$D$31)) | J16: =IF($A16="","",MAX(0,N($H16)-N($I16))) | L16: =IF($A16="","",N($I16)+N($J16)+N($K16)) | M16: =IF($A16="","",N($G16)-N($L16)) | N16: =IF($A16="","",IF(N($L16)>N($G16),"OVER",IF(N($L16)=N($G16),"ON PLAN","UNDER")))
F17: =IF($A17="","",SUMIF('Change Orders'!$C$2:$C$21,$A17,'Change Orders'!$G$2:$G$21)) | G17: =IF($A17="","",N($D17)+N($F17)) | H17: =IF($A17="","",N($E17)+N($F17)) | I17: =IF($A17="","",SUMIF(Payments!$B$2:$B$31,$A17,Payments!$D$2:$D$31)) | J17: =IF($A17="","",MAX(0,N($H17)-N($I17))) | L17: =IF($A17="","",N($I17)+N($J17)+N($K17)) | M17: =IF($A17="","",N($G17)-N($L17)) | N17: =IF($A17="","",IF(N($L17)>N($G17),"OVER",IF(N($L17)=N($G17),"ON PLAN","UNDER")))
F18: =IF($A18="","",SUMIF('Change Orders'!$C$2:$C$21,$A18,'Change Orders'!$G$2:$G$21)) | G18: =IF($A18="","",N($D18)+N($F18)) | H18: =IF($A18="","",N($E18)+N($F18)) | I18: =IF($A18="","",SUMIF(Payments!$B$2:$B$31,$A18,Payments!$D$2:$D$31)) | J18: =IF($A18="","",MAX(0,N($H18)-N($I18))) | L18: =IF($A18="","",N($I18)+N($J18)+N($K18)) | M18: =IF($A18="","",N($G18)-N($L18)) | N18: =IF($A18="","",IF(N($L18)>N($G18),"OVER",IF(N($L18)=N($G18),"ON PLAN","UNDER")))
F19: =IF($A19="","",SUMIF('Change Orders'!$C$2:$C$21,$A19,'Change Orders'!$G$2:$G$21)) | G19: =IF($A19="","",N($D19)+N($F19)) | H19: =IF($A19="","",N($E19)+N($F19)) | I19: =IF($A19="","",SUMIF(Payments!$B$2:$B$31,$A19,Payments!$D$2:$D$31)) | J19: =IF($A19="","",MAX(0,N($H19)-N($I19))) | L19: =IF($A19="","",N($I19)+N($J19)+N($K19)) | M19: =IF($A19="","",N($G19)-N($L19)) | N19: =IF($A19="","",IF(N($L19)>N($G19),"OVER",IF(N($L19)=N($G19),"ON PLAN","UNDER")))
F20: =IF($A20="","",SUMIF('Change Orders'!$C$2:$C$21,$A20,'Change Orders'!$G$2:$G$21)) | G20: =IF($A20="","",N($D20)+N($F20)) | H20: =IF($A20="","",N($E20)+N($F20)) | I20: =IF($A20="","",SUMIF(Payments!$B$2:$B$31,$A20,Payments!$D$2:$D$31)) | J20: =IF($A20="","",MAX(0,N($H20)-N($I20))) | L20: =IF($A20="","",N($I20)+N($J20)+N($K20)) | M20: =IF($A20="","",N($G20)-N($L20)) | N20: =IF($A20="","",IF(N($L20)>N($G20),"OVER",IF(N($L20)=N($G20),"ON PLAN","UNDER")))
F21: =IF($A21="","",SUMIF('Change Orders'!$C$2:$C$21,$A21,'Change Orders'!$G$2:$G$21)) | G21: =IF($A21="","",N($D21)+N($F21)) | H21: =IF($A21="","",N($E21)+N($F21)) | I21: =IF($A21="","",SUMIF(Payments!$B$2:$B$31,$A21,Payments!$D$2:$D$31)) | J21: =IF($A21="","",MAX(0,N($H21)-N($I21))) | L21: =IF($A21="","",N($I21)+N($J21)+N($K21)) | M21: =IF($A21="","",N($G21)-N($L21)) | N21: =IF($A21="","",IF(N($L21)>N($G21),"OVER",IF(N($L21)=N($G21),"ON PLAN","UNDER")))
F22: =IF($A22="","",SUMIF('Change Orders'!$C$2:$C$21,$A22,'Change Orders'!$G$2:$G$21)) | G22: =IF($A22="","",N($D22)+N($F22)) | H22: =IF($A22="","",N($E22)+N($F22)) | I22: =IF($A22="","",SUMIF(Payments!$B$2:$B$31,$A22,Payments!$D$2:$D$31)) | J22: =IF($A22="","",MAX(0,N($H22)-N($I22))) | L22: =IF($A22="","",N($I22)+N($J22)+N($K22)) | M22: =IF($A22="","",N($G22)-N($L22)) | N22: =IF($A22="","",IF(N($L22)>N($G22),"OVER",IF(N($L22)=N($G22),"ON PLAN","UNDER")))
... F40: =IF($A40="","",SUMIF('Change Orders'!$C$2:$C$21,$A40,'Change Orders'!$G$2:$G$21)) | G40: =IF($A40="","",N($D40)+N($F40)) | H40: =IF($A40="","",N($E40)+N($F40)) | I40: =IF($A40="","",SUMIF(Payments!$B$2:$B$31,$A40,Payments!$D$2:$D$31)) | J40: =IF($A40="","",MAX(0,N($H40)-N($I40))) | L40: =IF($A40="","",N($I40)+N($J40)+N($K40)) | M40: =IF($A40="","",N($G40)-N($L40)) | N40: =IF($A40="","",IF(N($L40)>N($G40),"OVER",IF(N($L40)=N($G40),"ON PLAN","UNDER")))

Sheet Change Orders
A1: CO # | B1: Date | C1: Line | D1: What changed | E1: Amount | F1: Approved? | G1: Amount that counts
A2: CO-01 | B2: 2026-05-20 | C2: K-03 | D2: Countertop selection above the allowance | E2: 1700 | F2: Yes | G2: =IF(OR($A2="",$E2=""),"",IF(LOWER(TRIM($F2))="yes",N($E2),0))
A3: CO-02 | B3: 2026-06-04 | C3: K-05 | D3: Added kitchen circuit required by inspection | E3: 600 | F3: Yes | G3: =IF(OR($A3="",$E3=""),"",IF(LOWER(TRIM($F3))="yes",N($E3),0))
A4: CO-03 | B4: 2026-06-18 | C4: K-06 | D4: Upgraded paint finish - not signed yet | E4: 450 | F4: No | G4: =IF(OR($A4="",$E4=""),"",IF(LOWER(TRIM($F4))="yes",N($E4),0))
G5: =IF(OR($A5="",$E5=""),"",IF(LOWER(TRIM($F5))="yes",N($E5),0))
G6: =IF(OR($A6="",$E6=""),"",IF(LOWER(TRIM($F6))="yes",N($E6),0))
G7: =IF(OR($A7="",$E7=""),"",IF(LOWER(TRIM($F7))="yes",N($E7),0))
G8: =IF(OR($A8="",$E8=""),"",IF(LOWER(TRIM($F8))="yes",N($E8),0))
G9: =IF(OR($A9="",$E9=""),"",IF(LOWER(TRIM($F9))="yes",N($E9),0))
G10: =IF(OR($A10="",$E10=""),"",IF(LOWER(TRIM($F10))="yes",N($E10),0))
G11: =IF(OR($A11="",$E11=""),"",IF(LOWER(TRIM($F11))="yes",N($E11),0))
G12: =IF(OR($A12="",$E12=""),"",IF(LOWER(TRIM($F12))="yes",N($E12),0))
G13: =IF(OR($A13="",$E13=""),"",IF(LOWER(TRIM($F13))="yes",N($E13),0))
G14: =IF(OR($A14="",$E14=""),"",IF(LOWER(TRIM($F14))="yes",N($E14),0))
G15: =IF(OR($A15="",$E15=""),"",IF(LOWER(TRIM($F15))="yes",N($E15),0))
G16: =IF(OR($A16="",$E16=""),"",IF(LOWER(TRIM($F16))="yes",N($E16),0))
... G20: =IF(OR($A20="",$E20=""),"",IF(LOWER(TRIM($F20))="yes",N($E20),0))

Sheet Allowances
A1: Allowance # | B1: Line | C1: Item | D1: Allowance in contract | E1: Chosen selection | F1: Difference | G1: Credit already received | H1: Credit still owed to you | I1: Change order # | J1: Status
A2: A-01 | B2: K-03 | C2: Countertops | D2: 7500 | E2: 9200 | F2: =IF($A2="","",IF(OR($D2="",$E2=""),"",N($E2)-N($D2))) | G2: 0 | H2: =IF($A2="","",IF(NOT(ISNUMBER($F2)),"",IF($F2<0,MAX(0,-N($F2)-N($G2)),0))) | I2: CO-01 | J2: =IF($A2="","",IF(NOT(ISNUMBER($F2)),"",IF($F2>0,IF($I2="","Overage - no change order #",IF(COUNTIFS('Change Orders'!$A$2:$A$21,$I2,'Change Orders'!$F$2:$F$21,"Yes")>0,"Overage - change order on file","Overage - CO not approved")),IF(N($H2)>0,"Credit still owed to you","Settled"))))
A3: A-02 | B3: K-06 | C3: Lighting | D3: 1200 | E3: 400 | F3: =IF($A3="","",IF(OR($D3="",$E3=""),"",N($E3)-N($D3))) | G3: 300 | H3: =IF($A3="","",IF(NOT(ISNUMBER($F3)),"",IF($F3<0,MAX(0,-N($F3)-N($G3)),0))) | J3: =IF($A3="","",IF(NOT(ISNUMBER($F3)),"",IF($F3>0,IF($I3="","Overage - no change order #",IF(COUNTIFS('Change Orders'!$A$2:$A$21,$I3,'Change Orders'!$F$2:$F$21,"Yes")>0,"Overage - change order on file","Overage - CO not approved")),IF(N($H3)>0,"Credit still owed to you","Settled"))))
A4: A-03 | B4: K-05 | C4: Plumbing fixtures | D4: 1500 | E4: 1900 | F4: =IF($A4="","",IF(OR($D4="",$E4=""),"",N($E4)-N($D4))) | G4: 0 | H4: =IF($A4="","",IF(NOT(ISNUMBER($F4)),"",IF($F4<0,MAX(0,-N($F4)-N($G4)),0))) | J4: =IF($A4="","",IF(NOT(ISNUMBER($F4)),"",IF($F4>0,IF($I4="","Overage - no change order #",IF(COUNTIFS('Change Orders'!$A$2:$A$21,$I4,'Change Orders'!$F$2:$F$21,"Yes")>0,"Overage - change order on file","Overage - CO not approved")),IF(N($H4)>0,"Credit still owed to you","Settled"))))
F5: =IF($A5="","",IF(OR($D5="",$E5=""),"",N($E5)-N($D5))) | H5: =IF($A5="","",IF(NOT(ISNUMBER($F5)),"",IF($F5<0,MAX(0,-N($F5)-N($G5)),0))) | J5: =IF($A5="","",IF(NOT(ISNUMBER($F5)),"",IF($F5>0,IF($I5="","Overage - no change order #",IF(COUNTIFS('Change Orders'!$A$2:$A$21,$I5,'Change Orders'!$F$2:$F$21,"Yes")>0,"Overage - change order on file","Overage - CO not approved")),IF(N($H5)>0,"Credit still owed to you","Settled"))))
F6: =IF($A6="","",IF(OR($D6="",$E6=""),"",N($E6)-N($D6))) | H6: =IF($A6="","",IF(NOT(ISNUMBER($F6)),"",IF($F6<0,MAX(0,-N($F6)-N($G6)),0))) | J6: =IF($A6="","",IF(NOT(ISNUMBER($F6)),"",IF($F6>0,IF($I6="","Overage - no change order #",IF(COUNTIFS('Change Orders'!$A$2:$A$21,$I6,'Change Orders'!$F$2:$F$21,"Yes")>0,"Overage - change order on file","Overage - CO not approved")),IF(N($H6)>0,"Credit still owed to you","Settled"))))
F7: =IF($A7="","",IF(OR($D7="",$E7=""),"",N($E7)-N($D7))) | H7: =IF($A7="","",IF(NOT(ISNUMBER($F7)),"",IF($F7<0,MAX(0,-N($F7)-N($G7)),0))) | J7: =IF($A7="","",IF(NOT(ISNUMBER($F7)),"",IF($F7>0,IF($I7="","Overage - no change order #",IF(COUNTIFS('Change Orders'!$A$2:$A$21,$I7,'Change Orders'!$F$2:$F$21,"Yes")>0,"Overage - change order on file","Overage - CO not approved")),IF(N($H7)>0,"Credit still owed to you","Settled"))))
F8: =IF($A8="","",IF(OR($D8="",$E8=""),"",N($E8)-N($D8))) | H8: =IF($A8="","",IF(NOT(ISNUMBER($F8)),"",IF($F8<0,MAX(0,-N($F8)-N($G8)),0))) | J8: =IF($A8="","",IF(NOT(ISNUMBER($F8)),"",IF($F8>0,IF($I8="","Overage - no change order #",IF(COUNTIFS('Change Orders'!$A$2:$A$21,$I8,'Change Orders'!$F$2:$F$21,"Yes")>0,"Overage - change order on file","Overage - CO not approved")),IF(N($H8)>0,"Credit still owed to you","Settled"))))
F9: =IF($A9="","",IF(OR($D9="",$E9=""),"",N($E9)-N($D9))) | H9: =IF($A9="","",IF(NOT(ISNUMBER($F9)),"",IF($F9<0,MAX(0,-N($F9)-N($G9)),0))) | J9: =IF($A9="","",IF(NOT(ISNUMBER($F9)),"",IF($F9>0,IF($I9="","Overage - no change order #",IF(COUNTIFS('Change Orders'!$A$2:$A$21,$I9,'Change Orders'!$F$2:$F$21,"Yes")>0,"Overage - change order on file","Overage - CO not approved")),IF(N($H9)>0,"Credit still owed to you","Settled"))))
F10: =IF($A10="","",IF(OR($D10="",$E10=""),"",N($E10)-N($D10))) | H10: =IF($A10="","",IF(NOT(ISNUMBER($F10)),"",IF($F10<0,MAX(0,-N($F10)-N($G10)),0))) | J10: =IF($A10="","",IF(NOT(ISNUMBER($F10)),"",IF($F10>0,IF($I10="","Overage - no change order #",IF(COUNTIFS('Change Orders'!$A$2:$A$21,$I10,'Change Orders'!$F$2:$F$21,"Yes")>0,"Overage - change order on file","Overage - CO not approved")),IF(N($H10)>0,"Credit still owed to you","Settled"))))
F11: =IF($A11="","",IF(OR($D11="",$E11=""),"",N($E11)-N($D11))) | H11: =IF($A11="","",IF(NOT(ISNUMBER($F11)),"",IF($F11<0,MAX(0,-N($F11)-N($G11)),0))) | J11: =IF($A11="","",IF(NOT(ISNUMBER($F11)),"",IF($F11>0,IF($I11="","Overage - no change order #",IF(COUNTIFS('Change Orders'!$A$2:$A$21,$I11,'Change Orders'!$F$2:$F$21,"Yes")>0,"Overage - change order on file","Overage - CO not approved")),IF(N($H11)>0,"Credit still owed to you","Settled"))))
F12: =IF($A12="","",IF(OR($D12="",$E12=""),"",N($E12)-N($D12))) | H12: =IF($A12="","",IF(NOT(ISNUMBER($F12)),"",IF($F12<0,MAX(0,-N($F12)-N($G12)),0))) | J12: =IF($A12="","",IF(NOT(ISNUMBER($F12)),"",IF($F12>0,IF($I12="","Overage - no change order #",IF(COUNTIFS('Change Orders'!$A$2:$A$21,$I12,'Change Orders'!$F$2:$F$21,"Yes")>0,"Overage - change order on file","Overage - CO not approved")),IF(N($H12)>0,"Credit still owed to you","Settled"))))
F13: =IF($A13="","",IF(OR($D13="",$E13=""),"",N($E13)-N($D13))) | H13: =IF($A13="","",IF(NOT(ISNUMBER($F13)),"",IF($F13<0,MAX(0,-N($F13)-N($G13)),0))) | J13: =IF($A13="","",IF(NOT(ISNUMBER($F13)),"",IF($F13>0,IF($I13="","Overage - no change order #",IF(COUNTIFS('Change Orders'!$A$2:$A$21,$I13,'Change Orders'!$F$2:$F$21,"Yes")>0,"Overage - change order on file","Overage - CO not approved")),IF(N($H13)>0,"Credit still owed to you","Settled"))))
F14: =IF($A14="","",IF(OR($D14="",$E14=""),"",N($E14)-N($D14))) | H14: =IF($A14="","",IF(NOT(ISNUMBER($F14)),"",IF($F14<0,MAX(0,-N($F14)-N($G14)),0))) | J14: =IF($A14="","",IF(NOT(ISNUMBER($F14)),"",IF($F14>0,IF($I14="","Overage - no change order #",IF(COUNTIFS('Change Orders'!$A$2:$A$21,$I14,'Change Orders'!$F$2:$F$21,"Yes")>0,"Overage - change order on file","Overage - CO not approved")),IF(N($H14)>0,"Credit still owed to you","Settled"))))
F15: =IF($A15="","",IF(OR($D15="",$E15=""),"",N($E15)-N($D15))) | H15: =IF($A15="","",IF(NOT(ISNUMBER($F15)),"",IF($F15<0,MAX(0,-N($F15)-N($G15)),0))) | J15: =IF($A15="","",IF(NOT(ISNUMBER($F15)),"",IF($F15>0,IF($I15="","Overage - no change order #",IF(COUNTIFS('Change Orders'!$A$2:$A$21,$I15,'Change Orders'!$F$2:$F$21,"Yes")>0,"Overage - change order on file","Overage - CO not approved")),IF(N($H15)>0,"Credit still owed to you","Settled"))))
F16: =IF($A16="","",IF(OR($D16="",$E16=""),"",N($E16)-N($D16))) | H16: =IF($A16="","",IF(NOT(ISNUMBER($F16)),"",IF($F16<0,MAX(0,-N($F16)-N($G16)),0))) | J16: =IF($A16="","",IF(NOT(ISNUMBER($F16)),"",IF($F16>0,IF($I16="","Overage - no change order #",IF(COUNTIFS('Change Orders'!$A$2:$A$21,$I16,'Change Orders'!$F$2:$F$21,"Yes")>0,"Overage - change order on file","Overage - CO not approved")),IF(N($H16)>0,"Credit still owed to you","Settled"))))
... F20: =IF($A20="","",IF(OR($D20="",$E20=""),"",N($E20)-N($D20))) | H20: =IF($A20="","",IF(NOT(ISNUMBER($F20)),"",IF($F20<0,MAX(0,-N($F20)-N($G20)),0))) | J20: =IF($A20="","",IF(NOT(ISNUMBER($F20)),"",IF($F20>0,IF($I20="","Overage - no change order #",IF(COUNTIFS('Change Orders'!$A$2:$A$21,$I20,'Change Orders'!$F$2:$F$21,"Yes")>0,"Overage - change order on file","Overage - CO not approved")),IF(N($H20)>0,"Credit still owed to you","Settled"))))

Sheet Payments
A1: Date | B1: Line | C1: Paid to | D1: Amount | E1: Method | F1: Note
A2: 2026-05-06 | B2: K-01 | C2: Demo crew | D2: 1400 | E2: Bank transfer | F2: 50% deposit
A3: 2026-05-18 | B3: K-02 | C3: Cabinet supplier | D3: 6250 | E3: Card | F3: 50% on order
A4: 2026-05-22 | B4: K-03 | C4: Stone fabricator | D4: 2250 | E4: Bank transfer | F4: 30% on template
A5: 2026-06-01 | B5: K-05 | C5: Electrician | D5: 2400 | E5: Bank transfer | F5: First invoice
A6: 2026-05-02 | B6: K-07 | C6: City permits office | D6: 1200 | E6: Card | F6: Permit issued
A7: 2026-06-02 | B7: K-09 | C7: Project manager | D7: 2800 | E7: Bank transfer | F7: Final fee

Sheet Contingency
A1: Date | B1: What the reserve paid for | C1: Amount | D1: Approved by | E1: Note | G1: Reserve remaining | H1: Drawn so far
A2: 2026-05-12 | B2: Hidden rot behind the sink wall | C2: 900 | D2: Owner | E2: Photos filed | G2: =IF(Setup!$B$5="","",N(Setup!$B$5)-SUM($C$2:$C$21)) | H2: =SUM($C$2:$C$21)
A3: 2026-06-03 | B3: Code-required outlet upgrade | C3: 1200 | D3: Owner | E3: Electrician letter filed

Sheet Assumptions
A1: # | B1: Type | C1: Statement | D1: Where it lives | E1: Owner's note
A2: 1 | B2: Excluded | C2: Temporary storage and rental furniture | D2: Not in any line | E2: Add a line if this becomes real
A3: 2 | B3: Excluded | C3: Landscaping and exterior work | D3: Out of scope this phase
A4: 3 | B4: Assumption | C4: Owner supplies appliances at retail price | E4: Quotes may move
A5: 4 | B5: Allowance | C5: Countertops priced at $7,500 until the slab is chosen | D5: A-01 | E5: Reconcile in Allowances
A6: 5 | B6: Risk | C6: House built before 1980 - hidden conditions likely | E6: Reserve sized at 10%; structural work may justify 25-30%

Sheet Summary
A1: Renovation cost control - summary
A2: =IF(Setup!$B$3="","(project name not set)",Setup!$B$3)
A4: Original budget (sum of lines) | B4: =SUM('Cost Control'!$D$2:$D$41)
A5: Approved change orders | B5: =SUM('Change Orders'!$G$2:$G$21)
A6: Revised budget | B6: =B4+B5
A7: Committed total | B7: =SUM('Cost Control'!$H$2:$H$41)
A8: Paid to date | B8: =SUM('Cost Control'!$I$2:$I$41)
A9: Unpaid committed | B9: =SUM('Cost Control'!$J$2:$J$41)
A10: Forecast to complete | B10: =SUM('Cost Control'!$K$2:$K$41)
A11: Projected final cost | B11: =SUM('Cost Control'!$L$2:$L$41)
A12: Variance vs revised budget | B12: =B6-B11
A13: Committed as % of revised budget | B13: =IF(B6=0,"",B7/B6)
A14: Contingency reserve remaining | B14: =Contingency!$G$2
A15: Allowance overruns (all) | B15: =SUMIF(Allowances!$F$2:$F$21,">0")
A16: Allowance credits still owed to you | B16: =SUM(Allowances!$H$2:$H$21)
A17: Change orders awaiting signature | B17: =COUNTIF('Change Orders'!$F$2:$F$21,"No")
A18: Lines already over their revised budget | B18: =COUNTIF('Cost Control'!$N$2:$N$41,"OVER")
A19: All-in plan (revised budget + reserve) | B19: =B6+B14
A21: Checks - fix anything that is not OK
A22: Any payment recorded against a line that does not exist? | B22: =IF(SUMPRODUCT((Payments!$D$2:$D$31<>"")*(COUNTIF('Cost Control'!$A$2:$A$41,Payments!$B$2:$B$31)=0))>0,"FIX: payment against an unknown line","OK")
A23: Any allowance overage with no approved change order? | B23: =IF(COUNTIF(Allowances!$J$2:$J$21,"Overage - no change order #")+COUNTIF(Allowances!$J$2:$J$21,"Overage - CO not approved")>0,"FIX: "&COUNTIF(Allowances!$J$2:$J$21,"Overage - no change order #")+COUNTIF(Allowances!$J$2:$J$21,"Overage - CO not approved")&" overage(s) with no approved change order","OK")
A24: Paid more than committed on any line? | B24: =IF(SUMPRODUCT(('Cost Control'!$I$2:$I$41>'Cost Control'!$H$2:$H$41)*('Cost Control'!$A$2:$A$41<>""))>0,"FIX: paid exceeds committed - check the line","OK")
A25: Projected final over revised budget? | B25: =IF(B12<0,"OVER by "&TEXT(-B12,"$#,##0"),"Within revised budget")
A26: Contingency reserve exhausted? | B26: =IF(B14<=0,"Reserve is gone - approve no more draws","Reserve still available")
A27: Remaining spend larger than what is left in the revised budget? | B27: =IF((B9+B10)>(B6-B8),"OVER-COMMITTED: remaining spend exceeds budget left","Remaining spend fits the budget")
A28: Any change order still marked No? | B28: =IF(B17>0,"Do not let the work proceed on an unsigned change","None pending")
A29: Any line with no original budget? | B29: =IF(SUMPRODUCT(('Cost Control'!$A$2:$A$41<>"")*('Cost Control'!$D$2:$D$41=""))>0,"FIX: line without a budget","OK")
A32: Blue cells are formulas. If a number looks wrong, check the row it came from - never overwrite a total.
