Workbook

Sheet HandoffRegister
A1: # | B1: Project | C1: Outgoing owner | D1: Incoming owner | E1: Handoff date | F1: Days to handoff | G1: Status | H1: Assets complete % | I1: Open high risks | J1: Client sign-off (Y/N) | K1: Close gate
A2: 1 | B2: EXAMPLE Website rebuild | C2: You | D2: Client team | E2: 2026-11-01 | F2: =IF(ISNUMBER(E2),E2-TODAY(),"") | G2: In progress | H2: =IF($B2="","",IFERROR(COUNTIFS(AssetChecklist!$A$2:$A$60,$B2,AssetChecklist!$D$2:$D$60,"Y")/COUNTIFS(AssetChecklist!$A$2:$A$60,$B2),"")) | I2: =IF($B2="","",COUNTIFS(RiskRegister!$A$2:$A$40,$B2,RiskRegister!$H$2:$H$40,"OPEN",RiskRegister!$F$2:$F$40,">=12")) | J2: N | K2: =IF($B2="","",IF($H2="","Fill the asset checklist first",IF(AND($H2>=1,$I2=0,$J2="Y"),"READY TO CLOSE","OPEN")))
A3: 2 | B3: EXAMPLE API integration | C3: You | D3: Agency B | E3: 2026-11-15 | F3: =IF(ISNUMBER(E3),E3-TODAY(),"") | G3: Not started | H3: =IF($B3="","",IFERROR(COUNTIFS(AssetChecklist!$A$2:$A$60,$B3,AssetChecklist!$D$2:$D$60,"Y")/COUNTIFS(AssetChecklist!$A$2:$A$60,$B3),"")) | I3: =IF($B3="","",COUNTIFS(RiskRegister!$A$2:$A$40,$B3,RiskRegister!$H$2:$H$40,"OPEN",RiskRegister!$F$2:$F$40,">=12")) | J3: N | K3: =IF($B3="","",IF($H3="","Fill the asset checklist first",IF(AND($H3>=1,$I3=0,$J3="Y"),"READY TO CLOSE","OPEN")))
A4: 3 | F4: =IF(ISNUMBER(E4),E4-TODAY(),"") | H4: =IF($B4="","",IFERROR(COUNTIFS(AssetChecklist!$A$2:$A$60,$B4,AssetChecklist!$D$2:$D$60,"Y")/COUNTIFS(AssetChecklist!$A$2:$A$60,$B4),"")) | I4: =IF($B4="","",COUNTIFS(RiskRegister!$A$2:$A$40,$B4,RiskRegister!$H$2:$H$40,"OPEN",RiskRegister!$F$2:$F$40,">=12")) | K4: =IF($B4="","",IF($H4="","Fill the asset checklist first",IF(AND($H4>=1,$I4=0,$J4="Y"),"READY TO CLOSE","OPEN")))
A5: 4 | F5: =IF(ISNUMBER(E5),E5-TODAY(),"") | H5: =IF($B5="","",IFERROR(COUNTIFS(AssetChecklist!$A$2:$A$60,$B5,AssetChecklist!$D$2:$D$60,"Y")/COUNTIFS(AssetChecklist!$A$2:$A$60,$B5),"")) | I5: =IF($B5="","",COUNTIFS(RiskRegister!$A$2:$A$40,$B5,RiskRegister!$H$2:$H$40,"OPEN",RiskRegister!$F$2:$F$40,">=12")) | K5: =IF($B5="","",IF($H5="","Fill the asset checklist first",IF(AND($H5>=1,$I5=0,$J5="Y"),"READY TO CLOSE","OPEN")))
A6: 5 | F6: =IF(ISNUMBER(E6),E6-TODAY(),"") | H6: =IF($B6="","",IFERROR(COUNTIFS(AssetChecklist!$A$2:$A$60,$B6,AssetChecklist!$D$2:$D$60,"Y")/COUNTIFS(AssetChecklist!$A$2:$A$60,$B6),"")) | I6: =IF($B6="","",COUNTIFS(RiskRegister!$A$2:$A$40,$B6,RiskRegister!$H$2:$H$40,"OPEN",RiskRegister!$F$2:$F$40,">=12")) | K6: =IF($B6="","",IF($H6="","Fill the asset checklist first",IF(AND($H6>=1,$I6=0,$J6="Y"),"READY TO CLOSE","OPEN")))
A7: 6 | F7: =IF(ISNUMBER(E7),E7-TODAY(),"") | H7: =IF($B7="","",IFERROR(COUNTIFS(AssetChecklist!$A$2:$A$60,$B7,AssetChecklist!$D$2:$D$60,"Y")/COUNTIFS(AssetChecklist!$A$2:$A$60,$B7),"")) | I7: =IF($B7="","",COUNTIFS(RiskRegister!$A$2:$A$40,$B7,RiskRegister!$H$2:$H$40,"OPEN",RiskRegister!$F$2:$F$40,">=12")) | K7: =IF($B7="","",IF($H7="","Fill the asset checklist first",IF(AND($H7>=1,$I7=0,$J7="Y"),"READY TO CLOSE","OPEN")))
A8: 7 | F8: =IF(ISNUMBER(E8),E8-TODAY(),"") | H8: =IF($B8="","",IFERROR(COUNTIFS(AssetChecklist!$A$2:$A$60,$B8,AssetChecklist!$D$2:$D$60,"Y")/COUNTIFS(AssetChecklist!$A$2:$A$60,$B8),"")) | I8: =IF($B8="","",COUNTIFS(RiskRegister!$A$2:$A$40,$B8,RiskRegister!$H$2:$H$40,"OPEN",RiskRegister!$F$2:$F$40,">=12")) | K8: =IF($B8="","",IF($H8="","Fill the asset checklist first",IF(AND($H8>=1,$I8=0,$J8="Y"),"READY TO CLOSE","OPEN")))
A9: 8 | F9: =IF(ISNUMBER(E9),E9-TODAY(),"") | H9: =IF($B9="","",IFERROR(COUNTIFS(AssetChecklist!$A$2:$A$60,$B9,AssetChecklist!$D$2:$D$60,"Y")/COUNTIFS(AssetChecklist!$A$2:$A$60,$B9),"")) | I9: =IF($B9="","",COUNTIFS(RiskRegister!$A$2:$A$40,$B9,RiskRegister!$H$2:$H$40,"OPEN",RiskRegister!$F$2:$F$40,">=12")) | K9: =IF($B9="","",IF($H9="","Fill the asset checklist first",IF(AND($H9>=1,$I9=0,$J9="Y"),"READY TO CLOSE","OPEN")))
A10: 9 | F10: =IF(ISNUMBER(E10),E10-TODAY(),"") | H10: =IF($B10="","",IFERROR(COUNTIFS(AssetChecklist!$A$2:$A$60,$B10,AssetChecklist!$D$2:$D$60,"Y")/COUNTIFS(AssetChecklist!$A$2:$A$60,$B10),"")) | I10: =IF($B10="","",COUNTIFS(RiskRegister!$A$2:$A$40,$B10,RiskRegister!$H$2:$H$40,"OPEN",RiskRegister!$F$2:$F$40,">=12")) | K10: =IF($B10="","",IF($H10="","Fill the asset checklist first",IF(AND($H10>=1,$I10=0,$J10="Y"),"READY TO CLOSE","OPEN")))
A11: 10 | F11: =IF(ISNUMBER(E11),E11-TODAY(),"") | H11: =IF($B11="","",IFERROR(COUNTIFS(AssetChecklist!$A$2:$A$60,$B11,AssetChecklist!$D$2:$D$60,"Y")/COUNTIFS(AssetChecklist!$A$2:$A$60,$B11),"")) | I11: =IF($B11="","",COUNTIFS(RiskRegister!$A$2:$A$40,$B11,RiskRegister!$H$2:$H$40,"OPEN",RiskRegister!$F$2:$F$40,">=12")) | K11: =IF($B11="","",IF($H11="","Fill the asset checklist first",IF(AND($H11>=1,$I11=0,$J11="Y"),"READY TO CLOSE","OPEN")))
A12: 11 | F12: =IF(ISNUMBER(E12),E12-TODAY(),"") | H12: =IF($B12="","",IFERROR(COUNTIFS(AssetChecklist!$A$2:$A$60,$B12,AssetChecklist!$D$2:$D$60,"Y")/COUNTIFS(AssetChecklist!$A$2:$A$60,$B12),"")) | I12: =IF($B12="","",COUNTIFS(RiskRegister!$A$2:$A$40,$B12,RiskRegister!$H$2:$H$40,"OPEN",RiskRegister!$F$2:$F$40,">=12")) | K12: =IF($B12="","",IF($H12="","Fill the asset checklist first",IF(AND($H12>=1,$I12=0,$J12="Y"),"READY TO CLOSE","OPEN")))
A13: 12 | F13: =IF(ISNUMBER(E13),E13-TODAY(),"") | H13: =IF($B13="","",IFERROR(COUNTIFS(AssetChecklist!$A$2:$A$60,$B13,AssetChecklist!$D$2:$D$60,"Y")/COUNTIFS(AssetChecklist!$A$2:$A$60,$B13),"")) | I13: =IF($B13="","",COUNTIFS(RiskRegister!$A$2:$A$40,$B13,RiskRegister!$H$2:$H$40,"OPEN",RiskRegister!$F$2:$F$40,">=12")) | K13: =IF($B13="","",IF($H13="","Fill the asset checklist first",IF(AND($H13>=1,$I13=0,$J13="Y"),"READY TO CLOSE","OPEN")))
A14: 13 | F14: =IF(ISNUMBER(E14),E14-TODAY(),"") | H14: =IF($B14="","",IFERROR(COUNTIFS(AssetChecklist!$A$2:$A$60,$B14,AssetChecklist!$D$2:$D$60,"Y")/COUNTIFS(AssetChecklist!$A$2:$A$60,$B14),"")) | I14: =IF($B14="","",COUNTIFS(RiskRegister!$A$2:$A$40,$B14,RiskRegister!$H$2:$H$40,"OPEN",RiskRegister!$F$2:$F$40,">=12")) | K14: =IF($B14="","",IF($H14="","Fill the asset checklist first",IF(AND($H14>=1,$I14=0,$J14="Y"),"READY TO CLOSE","OPEN")))
A15: 14 | F15: =IF(ISNUMBER(E15),E15-TODAY(),"") | H15: =IF($B15="","",IFERROR(COUNTIFS(AssetChecklist!$A$2:$A$60,$B15,AssetChecklist!$D$2:$D$60,"Y")/COUNTIFS(AssetChecklist!$A$2:$A$60,$B15),"")) | I15: =IF($B15="","",COUNTIFS(RiskRegister!$A$2:$A$40,$B15,RiskRegister!$H$2:$H$40,"OPEN",RiskRegister!$F$2:$F$40,">=12")) | K15: =IF($B15="","",IF($H15="","Fill the asset checklist first",IF(AND($H15>=1,$I15=0,$J15="Y"),"READY TO CLOSE","OPEN")))
A16: 15

Sheet ChecklistTemplate
A1: Category | B1: Item to transfer | C1: Why it prevents a dispute
A2: Code | B2: Repository ownership moved to the client org; their admins, not yours | C2: You keep write access and the 'transferred' claim is false
A3: Code | B3: Deploy keys / CI secrets reissued to the client and the old ones revoked | C3: A live key in your hands is a latent security incident
A4: Code | B4: Staging and production reproduced by the incoming owner, live, on the call | C4: A system they cannot run is not a system they own
A5: Docs | B5: Architecture notes: where everything lives and what depends on what | C5: The next integrator starts from zero without this map
A6: Docs | B6: Runbook: deploy, roll back, restart, rotate credentials | C6: An incident with no runbook becomes your unpaid emergency
A7: Docs | B7: Known-bugs list, written honestly, with severity | C7: Undisclosed bugs become 'you hid this' arguments
A8: Accounts | B8: Hosting, DNS, analytics, error tracking: transfer ownership, never share a password | C8: Shared passwords blur who changed what
A9: Accounts | B9: Every third-party API key reissued to a client-owned account | C9: The client must not depend on your account staying open
A10: Accounts | B10: Billing for the above moved to the client, verified on the call | C10: A silent recurring charge on your card is a dispute in month two
A11: Money | B11: Final invoice issued and payment terms stated in writing | C11: Scope disputes are usually money disputes in disguise
A12: Money | B12: Outstanding expenses and retainer balance reconciled to the cent | C12: Open money is the most common reason a handoff stalls
... A19: Support | B19: Support window: dates, what is covered, response time, and what costs extra | C19: An undefined window becomes free, permanent, unlimited support

Sheet AssetChecklist
A1: Project | B1: Category | C1: Item | D1: Access transferred (Y/N) | E1: Verified by | F1: Verified date | G1: Where it lives (URL / path) | H1: Proof note
A2: EXAMPLE Website rebuild | B2: Code | C2: Repo ownership + deploy keys | D2: N | G2: github.com/…
A3: EXAMPLE Website rebuild | B3: Accounts | C3: DNS registrar ownership | D3: N | G3: registrar login
A4: EXAMPLE Website rebuild | B4: Money | C4: Final invoice issued | D4: N

Sheet RiskRegister
A1: Project | B1: Risk (what could go wrong) | C1: Owner | D1: Severity 1-5 | E1: Likelihood 1-5 | F1: Score (S×L) | G1: Mitigation | H1: Status (OPEN/CLOSED) | I1: Due date | J1: A score of 12 or more (S×L) counts as a HIGH risk and blocks the close gate until it is CLOSED.
A2: EXAMPLE Website rebuild | B2: DNS transfer fails during the window | C2: You | D2: 4 | E2: 3 | F2: =IF(AND(ISNUMBER(D2),ISNUMBER(E2)),D2*E2,"") | G2: Lower TTL 48h before; keep old host warm for 72h | H2: OPEN | I2: 2026-10-30
F3: =IF(AND(ISNUMBER(D3),ISNUMBER(E3)),D3*E3,"")
F4: =IF(AND(ISNUMBER(D4),ISNUMBER(E4)),D4*E4,"")
F5: =IF(AND(ISNUMBER(D5),ISNUMBER(E5)),D5*E5,"")
F6: =IF(AND(ISNUMBER(D6),ISNUMBER(E6)),D6*E6,"")
F7: =IF(AND(ISNUMBER(D7),ISNUMBER(E7)),D7*E7,"")
F8: =IF(AND(ISNUMBER(D8),ISNUMBER(E8)),D8*E8,"")
F9: =IF(AND(ISNUMBER(D9),ISNUMBER(E9)),D9*E9,"")
F10: =IF(AND(ISNUMBER(D10),ISNUMBER(E10)),D10*E10,"")
F11: =IF(AND(ISNUMBER(D11),ISNUMBER(E11)),D11*E11,"")
F12: =IF(AND(ISNUMBER(D12),ISNUMBER(E12)),D12*E12,"")
F13: =IF(AND(ISNUMBER(D13),ISNUMBER(E13)),D13*E13,"")
F14: =IF(AND(ISNUMBER(D14),ISNUMBER(E14)),D14*E14,"")
... F39: =IF(AND(ISNUMBER(D39),ISNUMBER(E39)),D39*E39,"")

Sheet Dashboard
A1: KPI | B1: Value | C1: How it is computed
A2: Projects tracked | B2: =COUNTA(HandoffRegister!$B$2:$B$15) | C2: Named rows on HandoffRegister
A3: Projects READY TO CLOSE | B3: =COUNTIF(HandoffRegister!$K$2:$K$15,"READY TO CLOSE") | C3: Sign-off Y, assets 100%, no open high risks
A4: Sign-offs collected | B4: =COUNTIF(HandoffRegister!$J$2:$J$15,"Y") | C4: Client sign-off = Y
A5: Open HIGH risks | B5: =COUNTIFS(RiskRegister!$F$2:$F$40,">=12",RiskRegister!$H$2:$H$40,"OPEN") | C5: Score >= 12 and status OPEN
A6: Assets transferred (Y) | B6: =COUNTIF(AssetChecklist!$D$2:$D$60,"Y") | C6: Access transferred = Y
A7: Assets outstanding (N or blank) | B7: =COUNTA(AssetChecklist!$C$2:$C$60)-COUNTIF(AssetChecklist!$D$2:$D$60,"Y") | C7: Named checklist items not yet transferred
A8: Transfer readiness % | B8: =IFERROR(COUNTIF(AssetChecklist!$D$2:$D$60,"Y")/COUNTA(AssetChecklist!$C$2:$C$60),"") | C8: Transferred ÷ named items
A9: Next handoff in (days) | B9: =IFERROR(MIN(HandoffRegister!$F$2:$F$15),"") | C9: Smallest non-empty Days to handoff

Sheet README
A1: B12-002 Client Project Handoff Register — HOW TO USE
A3: 1) HandoffRegister: one row per project. Fill only the white cells. Blue cells compute (Days to handoff, Assets complete %, Open high risks, Close gate) and must not be overwritten. Yellow rows are EXAMPLES — overwrite or delete them.
A4: 2) AssetChecklist: add one row per item you are transferring, and set its Project name so it rolls up. Copy the exact items you need from ChecklistTemplate (Code, Docs, Accounts, Money, Data, Security, People, Support). Nothing counts as transferred until Access transferred = Y.
A5: 3) RiskRegister: log every handoff risk, score it Severity x Likelihood, and CLOSE the ones scoring 12 or more before you close the project. The close gate stays OPEN while a high risk is open.
A6: 4) Dashboard: reads the three sheets and shows transfer readiness, sign-offs, and the next handoff date. A project is 'READY TO CLOSE' only when its assets are 100%, it has no open high risks, and the client has signed off.
A7: 5) Use with the B12-002 PDF guide (the 45-minute session script and the copy-paste emails). This is a record-keeping tool, not legal advice.
